{
 "labels": ["midrange", "lands", "graveyard", "titania"],
 "player": "greg",
 "date": "2024-03-31",
 "games": [
  {
   "opponent": "casey",
   "winner": "greg"
  },
  {
   "opponent": "casey",
   "winner": "greg"
  }
 ],
 "matches": [
  {
   "opponent": "casey",
   "winner": "greg"
  }
 ],
 "mainboard": [
  {
   "name": "Bloodghast",
   "types": [
    "Creature"
   ],
   "sub_types": [
    "Vampire",
    "Spirit"
   ],
   "cmc": 2,
   "image": "",
   "colors": [
    "B"
   ],
   "mana_cost": "{B}{B}",
   "url": "https://scryfall.com/card/lcc/184/bloodghast?utm_source=api",
   "oracle_text": "Bloodghast can't block.\nBloodghast has haste as long as an opponent has 10 or less life.\nLandfall — Whenever a land enters the battlefield under your control, you may return Bloodghast from your graveyard to the battlefield."
  },
  {
   "name": "Stitcher's Supplier",
   "types": [
    "Creature"
   ],
   "sub_types": [
    "Zombie"
   ],
   "cmc": 1,
   "image": "",
   "colors": [
    "B"
   ],
   "mana_cost": "{B}",
   "url": "https://scryfall.com/card/m19/121/stitchers-supplier?utm_source=api",
   "oracle_text": "When Stitcher's Supplier enters the battlefield or dies, mill three cards."
  },
  {
   "name": "Lightning Greaves",
   "types": [
    "Artifact"
   ],
   "sub_types": [
    "Equipment"
   ],
   "cmc": 2,
   "image": "",
   "colors": [],
   "mana_cost": "{2}",
   "url": "https://scryfall.com/card/cmm/398/lightning-greaves?utm_source=api",
   "oracle_text": "Equipped creature has haste and shroud. (It can't be the target of spells or abilities.)\nEquip {0}"
  },
  {
   "name": "Verdant Catacombs",
   "types": [
    "Land"
   ],
   "cmc": 0,
   "image": "",
   "colors": [],
   "mana_cost": "",
   "url": "https://scryfall.com/card/mh2/260/verdant-catacombs?utm_source=api",
   "oracle_text": "{T}, Pay 1 life, Sacrifice Verdant Catacombs: Search your library for a Swamp or Forest card, put it onto the battlefield, then shuffle."
  },
  {
   "name": "Life from the Loam",
   "types": [
    "Sorcery"
   ],
   "cmc": 2,
   "image": "",
   "colors": [
    "G"
   ],
   "mana_cost": "{1}{G}",
   "url": "https://scryfall.com/card/rvr/148/life-from-the-loam?utm_source=api",
   "oracle_text": "Return up to three target land cards from your graveyard to your hand.\nDredge 3 (If you would draw a card, you may mill three cards instead. If you do, return this card from your graveyard to your hand.)"
  },
  {
   "name": "Virtue of Persistence // Locthwain Scorn",
   "types": [
    "Enchantment",
    "//",
    "Sorcery"
   ],
   "sub_types": [
    "Adventure"
   ],
   "cmc": 7,
   "image": "",
   "colors": [
    "B"
   ],
   "mana_cost": "{5}{B}{B} // {1}{B}",
   "url": "https://scryfall.com/card/woe/115/virtue-of-persistence-locthwain-scorn?utm_source=api",
   "oracle_text": ""
  },
  {
   "name": "Satyr Wayfinder",
   "types": [
    "Creature"
   ],
   "sub_types": [
    "Satyr"
   ],
   "cmc": 2,
   "image": "",
   "colors": [
    "G"
   ],
   "mana_cost": "{1}{G}",
   "url": "https://scryfall.com/card/znc/81/satyr-wayfinder?utm_source=api",
   "oracle_text": "When Satyr Wayfinder enters the battlefield, reveal the top four cards of your library. You may put a land card from among them into your hand. Put the rest into your graveyard."
  },
  {
   "name": "Scattered Groves",
   "types": [
    "Land"
   ],
   "sub_types": [
    "Forest",
    "Plains"
   ],
   "cmc": 0,
   "image": "",
   "colors": [],
   "mana_cost": "",
   "url": "https://scryfall.com/card/mkc/286/scattered-groves?utm_source=api",
   "oracle_text": "({T}: Add {G} or {W}.)\nScattered Groves enters the battlefield tapped.\nCycling {2} ({2}, Discard this card: Draw a card.)"
  },
  {
   "name": "Devoted Druid",
   "types": [
    "Creature"
   ],
   "sub_types": [
    "Elf",
    "Druid"
   ],
   "cmc": 2,
   "image": "",
   "colors": [
    "G"
   ],
   "mana_cost": "{1}{G}",
   "url": "https://scryfall.com/card/2x2/143/devoted-druid?utm_source=api",
   "oracle_text": "{T}: Add {G}.\nPut a -1/-1 counter on Devoted Druid: Untap Devoted Druid."
  },
  {
   "name": "Knight of the Reliquary",
   "types": [
    "Creature"
   ],
   "sub_types": [
    "Human",
    "Knight"
   ],
   "cmc": 3,
   "image": "",
   "colors": [
    "G",
    "W"
   ],
   "mana_cost": "{1}{G}{W}",
   "url": "https://scryfall.com/card/ima/203/knight-of-the-reliquary?utm_source=api",
   "oracle_text": "Knight of the Reliquary gets +1/+1 for each land card in your graveyard.\n{T}, Sacrifice a Forest or Plains: Search your library for a land card, put it onto the battlefield, then shuffle."
  },
  {
   "name": "Crop Rotation",
   "types": [
    "Instant"
   ],
   "cmc": 1,
   "image": "",
   "colors": [
    "G"
   ],
   "mana_cost": "{G}",
   "url": "https://scryfall.com/card/dmr/154/crop-rotation?utm_source=api",
   "oracle_text": "As an additional cost to cast this spell, sacrifice a land.\nSearch your library for a land card, put that card onto the battlefield, then shuffle."
  },
  {
   "name": "Edge of Autumn",
   "types": [
    "Sorcery"
   ],
   "cmc": 2,
   "image": "",
   "colors": [
    "G"
   ],
   "mana_cost": "{1}{G}",
   "url": "https://scryfall.com/card/tsr/201/edge-of-autumn?utm_source=api",
   "oracle_text": "If you control four or fewer lands, search your library for a basic land card, put it onto the battlefield tapped, then shuffle.\nCycling—Sacrifice a land. (Sacrifice a land, Discard this card: Draw a card.)"
  },
  {
   "name": "Worm Harvest",
   "types": [
    "Sorcery"
   ],
   "cmc": 5,
   "image": "",
   "colors": [
    "B",
    "G"
   ],
   "mana_cost": "{2}{B/G}{B/G}{B/G}",
   "url": "https://scryfall.com/card/c18/194/worm-harvest?utm_source=api",
   "oracle_text": "Create a 1/1 black and green Worm creature token for each land card in your graveyard.\nRetrace (You may cast this card from your graveyard by discarding a land card in addition to paying its other costs.)"
  },
  {
   "name": "The Wandering Emperor",
   "types": [
    "Legendary",
    "Planeswalker"
   ],
   "cmc": 4,
   "image": "",
   "colors": [
    "W"
   ],
   "mana_cost": "{2}{W}{W}",
   "url": "https://scryfall.com/card/neo/42/the-wandering-emperor?utm_source=api",
   "oracle_text": "Flash\nAs long as The Wandering Emperor entered the battlefield this turn, you may activate her loyalty abilities any time you could cast an instant.\n+1: Put a +1/+1 counter on up to one target creature. It gains first strike until end of turn.\n−1: Create a 2/2 white Samurai creature token with vigilance.\n−2: Exile target tapped creature. You gain 2 life."
  },
  {
   "name": "Prismatic Vista",
   "types": [
    "Land"
   ],
   "cmc": 0,
   "image": "",
   "colors": [],
   "mana_cost": "",
   "url": "https://scryfall.com/card/mh1/244/prismatic-vista?utm_source=api",
   "oracle_text": "{T}, Pay 1 life, Sacrifice Prismatic Vista: Search your library for a basic land card, put it onto the battlefield, then shuffle."
  },
  {
   "name": "Courser of Kruphix",
   "types": [
    "Enchantment",
    "Creature"
   ],
   "sub_types": [
    "Centaur"
   ],
   "cmc": 3,
   "image": "",
   "colors": [
    "G"
   ],
   "mana_cost": "{1}{G}{G}",
   "url": "https://scryfall.com/card/cmm/888/courser-of-kruphix?utm_source=api",
   "oracle_text": "Play with the top card of your library revealed.\nYou may play lands from the top of your library.\nLandfall — Whenever a land enters the battlefield under your control, you gain 1 life."
  },
  {
   "name": "Chainweb Aracnir",
   "types": [
    "Creature"
   ],
   "sub_types": [
    "Spider"
   ],
   "cmc": 1,
   "image": "",
   "colors": [
    "G"
   ],
   "mana_cost": "{G}",
   "url": "https://scryfall.com/card/thb/167/chainweb-aracnir?utm_source=api",
   "oracle_text": "Reach\nWhen Chainweb Aracnir enters the battlefield, it deals damage equal to its power to target creature with flying an opponent controls.\nEscape—{3}{G}{G}, Exile four other cards from your graveyard. (You may cast this card from your graveyard for its escape cost.)\nChainweb Aracnir escapes with three +1/+1 counters on it."
  },
  {
   "name": "Harrow",
   "types": [
    "Instant"
   ],
   "cmc": 3,
   "image": "",
   "colors": [
    "G"
   ],
   "mana_cost": "{2}{G}",
   "url": "https://scryfall.com/card/znc/69/harrow?utm_source=api",
   "oracle_text": "As an additional cost to cast this spell, sacrifice a land.\nSearch your library for up to two basic land cards, put them onto the battlefield, then shuffle."
  },
  {
   "name": "Nurturing Peatland",
   "types": [
    "Land"
   ],
   "cmc": 0,
   "image": "",
   "colors": [],
   "mana_cost": "",
   "url": "https://scryfall.com/card/mh1/243/nurturing-peatland?utm_source=api",
   "oracle_text": "{T}, Pay 1 life: Add {B} or {G}.\n{1}, {T}, Sacrifice Nurturing Peatland: Draw a card."
  },
  {
   "name": "Canopy Vista",
   "types": [
    "Land"
   ],
   "sub_types": [
    "Forest",
    "Plains"
   ],
   "cmc": 0,
   "image": "",
   "colors": [],
   "mana_cost": "",
   "url": "https://scryfall.com/card/mkc/252/canopy-vista?utm_source=api",
   "oracle_text": "({T}: Add {G} or {W}.)\nCanopy Vista enters the battlefield tapped unless you control two or more basic lands."
  },
  {
   "name": "The Binding of the Titans",
   "types": [
    "Enchantment"
   ],
   "sub_types": [
    "Saga"
   ],
   "cmc": 2,
   "image": "",
   "colors": [
    "G"
   ],
   "mana_cost": "{1}{G}",
   "url": "https://scryfall.com/card/cmm/886/the-binding-of-the-titans?utm_source=api",
   "oracle_text": "(As this Saga enters and after your draw step, add a lore counter. Sacrifice after III.)\nI — Each player mills three cards.\nII — Exile up to two target cards from graveyards. For each creature card exiled this way, you gain 1 life.\nIII — Return target creature or land card from your graveyard to your hand."
  },
  {
   "name": "Mosswood Dreadknight // Dread Whispers",
   "types": [
    "Creature"
   ],
   "sub_types": [
    "Human",
    "Knight",
    "//",
    "Sorcery"
   ],
   "cmc": 2,
   "image": "",
   "colors": [
    "G"
   ],
   "mana_cost": "{1}{G} // {1}{B}",
   "url": "https://scryfall.com/card/woe/231/mosswood-dreadknight-dread-whispers?utm_source=api",
   "oracle_text": ""
  },
  {
   "name": "Song of the Dryads",
   "types": [
    "Enchantment"
   ],
   "sub_types": [
    "Aura"
   ],
   "cmc": 3,
   "image": "",
   "colors": [
    "G"
   ],
   "mana_cost": "{2}{G}",
   "url": "https://scryfall.com/card/cmm/324/song-of-the-dryads?utm_source=api",
   "oracle_text": "Enchant permanent\nEnchanted permanent is a colorless Forest land."
  },
  {
   "name": "Titania, Protector of Argoth",
   "types": [
    "Legendary",
    "Creature"
   ],
   "sub_types": [
    "Elemental"
   ],
   "cmc": 5,
   "image": "",
   "colors": [
    "G"
   ],
   "mana_cost": "{3}{G}{G}",
   "url": "https://scryfall.com/card/mh2/287/titania-protector-of-argoth?utm_source=api",
   "oracle_text": "When Titania, Protector of Argoth enters the battlefield, return target land card from your graveyard to the battlefield.\nWhenever a land you control is put into a graveyard from the battlefield, create a 5/3 green Elemental creature token."
  },
  {
   "name": "Windswept Heath",
   "types": [
    "Land"
   ],
   "cmc": 0,
   "image": "",
   "colors": [],
   "mana_cost": "",
   "url": "https://scryfall.com/card/mh3/235/windswept-heath?utm_source=api",
   "oracle_text": "{T}, Pay 1 life, Sacrifice Windswept Heath: Search your library for a Forest or Plains card, put it onto the battlefield, then shuffle."
  },
  {
   "name": "Grim Discovery",
   "types": [
    "Sorcery"
   ],
   "cmc": 2,
   "image": "",
   "colors": [
    "B"
   ],
   "mana_cost": "{1}{B}",
   "url": "https://scryfall.com/card/ddr/51/grim-discovery?utm_source=api",
   "oracle_text": "Choose one or both —\n• Return target creature card from your graveyard to your hand.\n• Return target land card from your graveyard to your hand."
  },
  {
   "name": "Infernal Grasp",
   "types": [
    "Instant"
   ],
   "cmc": 2,
   "image": "",
   "colors": [
    "B"
   ],
   "mana_cost": "{1}{B}",
   "url": "https://scryfall.com/card/mid/107/infernal-grasp?utm_source=api",
   "oracle_text": "Destroy target creature. You lose 2 life."
  },
  {
   "name": "Horizon Canopy",
   "types": [
    "Land"
   ],
   "cmc": 0,
   "image": "",
   "colors": [],
   "mana_cost": "",
   "url": "https://scryfall.com/card/ima/240/horizon-canopy?utm_source=api",
   "oracle_text": "{T}, Pay 1 life: Add {G} or {W}.\n{1}, {T}, Sacrifice Horizon Canopy: Draw a card."
  },
  {
   "name": "Marshal's Anthem",
   "types": [
    "Enchantment"
   ],
   "cmc": 4,
   "image": "",
   "colors": [
    "W"
   ],
   "mana_cost": "{2}{W}{W}",
   "url": "https://scryfall.com/card/khc/29/marshals-anthem?utm_source=api",
   "oracle_text": "Multikicker {1}{W} (You may pay an additional {1}{W} any number of times as you cast this spell.)\nCreatures you control get +1/+1.\nWhen Marshal's Anthem enters the battlefield, return up to X target creature cards from your graveyard to the battlefield, where X is the number of times Marshal's Anthem was kicked."
  },
  {
   "name": "Arbor Elf",
   "types": [
    "Creature"
   ],
   "sub_types": [
    "Elf",
    "Druid"
   ],
   "cmc": 1,
   "image": "",
   "colors": [
    "G"
   ],
   "mana_cost": "{G}",
   "url": "https://scryfall.com/card/a25/160/arbor-elf?utm_source=api",
   "oracle_text": "{T}: Untap target Forest."
  },
  {
   "name": "Eternal Witness",
   "types": [
    "Creature"
   ],
   "sub_types": [
    "Human",
    "Shaman"
   ],
   "cmc": 3,
   "image": "",
   "colors": [
    "G"
   ],
   "mana_cost": "{1}{G}{G}",
   "url": "https://scryfall.com/card/cmm/286/eternal-witness?utm_source=api",
   "oracle_text": "When Eternal Witness enters the battlefield, you may return target card from your graveyard to your hand."
  },
  {
   "name": "Cloudgoat Ranger",
   "types": [
    "Creature"
   ],
   "sub_types": [
    "Giant",
    "Warrior",
    "Ranger"
   ],
   "cmc": 5,
   "image": "",
   "colors": [
    "W"
   ],
   "mana_cost": "{3}{W}{W}",
   "url": "https://scryfall.com/card/khc/21/cloudgoat-ranger?utm_source=api",
   "oracle_text": "When Cloudgoat Ranger enters the battlefield, create three 1/1 white Kithkin Soldier creature tokens.\nTap three untapped Kithkin you control: Cloudgoat Ranger gets +2/+0 and gains flying until end of turn."
  },
  {
   "name": "Plains",
   "types": [
    "Basic",
    "Land"
   ],
   "sub_types": [
    "Plains"
   ],
   "cmc": 0,
   "image": "",
   "colors": [],
   "mana_cost": "",
   "url": "https://scryfall.com/card/mh3/304/plains?utm_source=api",
   "oracle_text": "({T}: Add {W}.)"
  },
  {
   "name": "Plains",
   "types": [
    "Basic",
    "Land"
   ],
   "sub_types": [
    "Plains"
   ],
   "cmc": 0,
   "image": "",
   "colors": [],
   "mana_cost": "",
   "url": "https://scryfall.com/card/mh3/304/plains?utm_source=api",
   "oracle_text": "({T}: Add {W}.)"
  },
  {
   "name": "Swamp",
   "types": [
    "Basic",
    "Land"
   ],
   "sub_types": [
    "Swamp"
   ],
   "cmc": 0,
   "image": "",
   "colors": [],
   "mana_cost": "",
   "url": "https://scryfall.com/card/mh3/306/swamp?utm_source=api",
   "oracle_text": "({T}: Add {B}.)"
  },
  {
   "name": "Swamp",
   "types": [
    "Basic",
    "Land"
   ],
   "sub_types": [
    "Swamp"
   ],
   "cmc": 0,
   "image": "",
   "colors": [],
   "mana_cost": "",
   "url": "https://scryfall.com/card/mh3/306/swamp?utm_source=api",
   "oracle_text": "({T}: Add {B}.)"
  },
  {
   "name": "Forest",
   "types": [
    "Basic",
    "Land"
   ],
   "sub_types": [
    "Forest"
   ],
   "cmc": 0,
   "image": "",
   "colors": [],
   "mana_cost": "",
   "url": "https://scryfall.com/card/mh3/308/forest?utm_source=api",
   "oracle_text": "({T}: Add {G}.)"
  },
  {
   "name": "Forest",
   "types": [
    "Basic",
    "Land"
   ],
   "sub_types": [
    "Forest"
   ],
   "cmc": 0,
   "image": "",
   "colors": [],
   "mana_cost": "",
   "url": "https://scryfall.com/card/mh3/308/forest?utm_source=api",
   "oracle_text": "({T}: Add {G}.)"
  },
  {
   "name": "Forest",
   "types": [
    "Basic",
    "Land"
   ],
   "sub_types": [
    "Forest"
   ],
   "cmc": 0,
   "image": "",
   "colors": [],
   "mana_cost": "",
   "url": "https://scryfall.com/card/mh3/308/forest?utm_source=api",
   "oracle_text": "({T}: Add {G}.)"
  },
  {
   "name": "Forest",
   "types": [
    "Basic",
    "Land"
   ],
   "sub_types": [
    "Forest"
   ],
   "cmc": 0,
   "image": "",
   "colors": [],
   "mana_cost": "",
   "url": "https://scryfall.com/card/mh3/308/forest?utm_source=api",
   "oracle_text": "({T}: Add {G}.)"
  }
 ],
 "sideboard": [
  {
   "name": "Ephara's Dispersal",
   "types": [
    "Instant"
   ],
   "cmc": 3,
   "image": "",
   "colors": [
    "U"
   ],
   "mana_cost": "{2}{U}",
   "url": "https://scryfall.com/card/mkc/103/epharas-dispersal?utm_source=api",
   "oracle_text": "This spell costs {2} less to cast if it targets an attacking creature.\nReturn target creature to its owner's hand. Surveil 2. (Look at the top two cards of your library, then put any number of them into your graveyard and the rest on top of your library in any order.)"
  },
  {
   "name": "Misty Rainforest",
   "types": [
    "Land"
   ],
   "cmc": 0,
   "image": "",
   "colors": [],
   "mana_cost": "",
   "url": "https://scryfall.com/card/mh2/250/misty-rainforest?utm_source=api",
   "oracle_text": "{T}, Pay 1 life, Sacrifice Misty Rainforest: Search your library for a Forest or Island card, put it onto the battlefield, then shuffle."
  },
  {
   "name": "Gilder Bairn",
   "types": [
    "Creature"
   ],
   "sub_types": [
    "Ouphe"
   ],
   "cmc": 3,
   "image": "",
   "colors": [
    "G",
    "U"
   ],
   "mana_cost": "{1}{G/U}{G/U}",
   "url": "https://scryfall.com/card/eve/152/gilder-bairn?utm_source=api",
   "oracle_text": "{2}{G/U}, {Q}: Double the number of each kind of counter on target permanent. ({Q} is the untap symbol.)"
  },
  {
   "name": "Brineborn Cutthroat",
   "types": [
    "Creature"
   ],
   "sub_types": [
    "Merfolk",
    "Pirate"
   ],
   "cmc": 2,
   "image": "",
   "colors": [
    "U"
   ],
   "mana_cost": "{1}{U}",
   "url": "https://scryfall.com/card/m20/50/brineborn-cutthroat?utm_source=api",
   "oracle_text": "Flash (You may cast this spell any time you could cast an instant.)\nWhenever you cast a spell during an opponent's turn, put a +1/+1 counter on Brineborn Cutthroat."
  },
  {
   "name": "Panharmonicon",
   "types": [
    "Artifact"
   ],
   "cmc": 4,
   "image": "",
   "colors": [],
   "mana_cost": "{4}",
   "url": "https://scryfall.com/card/2x2/310/panharmonicon?utm_source=api",
   "oracle_text": "If an artifact or creature entering the battlefield causes a triggered ability of a permanent you control to trigger, that ability triggers an additional time."
  },
  {
   "name": "Mosquito Guard",
   "types": [
    "Creature"
   ],
   "sub_types": [
    "Kithkin",
    "Soldier"
   ],
   "cmc": 1,
   "image": "",
   "colors": [
    "W"
   ],
   "mana_cost": "{W}",
   "url": "https://scryfall.com/card/ddf/6/mosquito-guard?utm_source=api",
   "oracle_text": "First strike\nReinforce 1—{1}{W} ({1}{W}, Discard this card: Put a +1/+1 counter on target creature.)"
  },
  {
   "name": "Warden of the Inner Sky",
   "types": [
    "Creature"
   ],
   "sub_types": [
    "Human",
    "Soldier"
   ],
   "cmc": 1,
   "image": "",
   "colors": [
    "W"
   ],
   "mana_cost": "{W}",
   "url": "https://scryfall.com/card/lci/43/warden-of-the-inner-sky?utm_source=api",
   "oracle_text": "As long as Warden of the Inner Sky has three or more counters on it, it has flying and vigilance.\nTap three untapped artifacts and/or creatures you control: Put a +1/+1 counter on Warden of the Inner Sky. Scry 1. Activate only as a sorcery."
  },
  {
   "name": "Spirited Companion",
   "types": [
    "Enchantment",
    "Creature"
   ],
   "sub_types": [
    "Dog"
   ],
   "cmc": 2,
   "image": "",
   "colors": [
    "W"
   ],
   "mana_cost": "{1}{W}",
   "url": "https://scryfall.com/card/cmm/838/spirited-companion?utm_source=api",
   "oracle_text": "When Spirited Companion enters the battlefield, draw a card."
  },
  {
   "name": "Reclamation Sage",
   "types": [
    "Creature"
   ],
   "sub_types": [
    "Elf",
    "Shaman"
   ],
   "cmc": 3,
   "image": "",
   "colors": [
    "G"
   ],
   "mana_cost": "{2}{G}",
   "url": "https://scryfall.com/card/khc/72/reclamation-sage?utm_source=api",
   "oracle_text": "When Reclamation Sage enters the battlefield, you may destroy target artifact or enchantment."
  },
  {
   "name": "Turn to Mist",
   "types": [
    "Instant"
   ],
   "cmc": 2,
   "image": "",
   "colors": [
    "U",
    "W"
   ],
   "mana_cost": "{1}{W/U}",
   "url": "https://scryfall.com/card/clu/214/turn-to-mist?utm_source=api",
   "oracle_text": "Exile target creature. Return that card to the battlefield under its owner's control at the beginning of the next end step."
  },
  {
   "name": "Traverse the Ulvenwald",
   "types": [
    "Sorcery"
   ],
   "cmc": 1,
   "image": "",
   "colors": [
    "G"
   ],
   "mana_cost": "{G}",
   "url": "https://scryfall.com/card/soi/234/traverse-the-ulvenwald?utm_source=api",
   "oracle_text": "Search your library for a basic land card, reveal it, put it into your hand, then shuffle.\nDelirium — If there are four or more card types among cards in your graveyard, instead search your library for a creature or land card, reveal it, put it into your hand, then shuffle."
  },
  {
   "name": "Hardened Scales",
   "types": [
    "Enchantment"
   ],
   "cmc": 1,
   "image": "",
   "colors": [
    "G"
   ],
   "mana_cost": "{G}",
   "url": "https://scryfall.com/card/lcc/243/hardened-scales?utm_source=api",
   "oracle_text": "If one or more +1/+1 counters would be put on a creature you control, that many plus one +1/+1 counters are put on it instead."
  },
  {
   "name": "Gilded Goose",
   "types": [
    "Creature"
   ],
   "sub_types": [
    "Bird"
   ],
   "cmc": 1,
   "image": "",
   "colors": [
    "G"
   ],
   "mana_cost": "{G}",
   "url": "https://scryfall.com/card/moc/299/gilded-goose?utm_source=api",
   "oracle_text": "Flying\nWhen Gilded Goose enters the battlefield, create a Food token. (It's an artifact with \"{2}, {T}, Sacrifice this artifact: You gain 3 life.\")\n{1}{G}, {T}: Create a Food token.\n{T}, Sacrifice a Food: Add one mana of any color."
  }
 ]
}
