{
 "metadata": {
  "path": "data/polyverse/2024-01-07/jen.json",
  "draft_id": "2024-01-07",
  "combined_file": "data/polyverse/2024-01-07/jen.txt"
 },
 "labels": [
  "midrange",
  "+1/+1",
  "token"
 ],
 "player": "jen",
 "date": "2024-01-07",
 "games": [
  {
   "opponent": "casey",
   "winner": "casey"
  },
  {
   "opponent": "casey",
   "winner": "jen"
  },
  {
   "opponent": "dom",
   "winner": "dom"
  },
  {
   "opponent": "dom",
   "winner": "dom"
  },
  {
   "opponent": "greg",
   "winner": "jen"
  },
  {
   "opponent": "greg",
   "winner": "greg"
  },
  {
   "opponent": "greg",
   "winner": "greg"
  },
  {
   "opponent": "james",
   "winner": "jen"
  },
  {
   "opponent": "james",
   "winner": "james"
  },
  {
   "opponent": "james",
   "winner": "james"
  }
 ],
 "matches": [
  {
   "opponent": "dom",
   "winner": "dom"
  },
  {
   "opponent": "greg",
   "winner": "greg"
  },
  {
   "opponent": "james",
   "winner": "james"
  }
 ],
 "mainboard": [
  {
   "name": "Flickerwisp",
   "types": [
    "Creature"
   ],
   "sub_types": [
    "Elemental"
   ],
   "cmc": 3,
   "image": "",
   "colors": [
    "W"
   ],
   "color_identity": [
    "W"
   ],
   "mana_cost": "{1}{W}{W}",
   "url": "https://scryfall.com/card/2x2/11/flickerwisp?utm_source=api",
   "oracle_text": "Flying\nWhen this creature enters, exile another target permanent. Return that card to the battlefield under its owner's control at the beginning of the next end step.",
   "power": "3",
   "toughness": "1",
   "appearances": 1
  },
  {
   "name": "The Wandering Emperor",
   "types": [
    "Legendary",
    "Planeswalker"
   ],
   "cmc": 4,
   "image": "",
   "colors": [
    "W"
   ],
   "color_identity": [
    "W"
   ],
   "mana_cost": "{2}{W}{W}",
   "url": "https://scryfall.com/card/neo/42/the-wandering-emperor?utm_source=api",
   "oracle_text": "Flash\nAs long as The Wandering Emperor entered this turn, you may activate her loyalty abilities any time you could cast an instant.\n+1: Put a +1/+1 counter on up to one target creature. It gains first strike until end of turn.\n−1: Create a 2/2 white Samurai creature token with vigilance.\n−2: Exile target tapped creature. You gain 2 life.",
   "appearances": 1
  },
  {
   "name": "Tail Swipe",
   "types": [
    "Instant"
   ],
   "cmc": 1,
   "image": "",
   "colors": [
    "G"
   ],
   "color_identity": [
    "G"
   ],
   "mana_cost": "{G}",
   "url": "https://scryfall.com/card/dmu/182/tail-swipe?utm_source=api",
   "oracle_text": "Choose target creature you control and target creature you don't control. If you cast this spell during your main phase, the creature you control gets +1/+1 until end of turn. Then those creatures fight each other. (Each deals damage equal to its power to the other.)",
   "appearances": 1
  },
  {
   "name": "Shanna, Sisay's Legacy",
   "types": [
    "Legendary",
    "Creature"
   ],
   "sub_types": [
    "Human",
    "Warrior"
   ],
   "cmc": 2,
   "image": "",
   "colors": [
    "G",
    "W"
   ],
   "color_identity": [
    "G",
    "W"
   ],
   "mana_cost": "{G}{W}",
   "url": "https://scryfall.com/card/dom/204/shanna-sisays-legacy?utm_source=api",
   "oracle_text": "Shanna can't be the target of abilities your opponents control.\nShanna gets +1/+1 for each creature you control.",
   "power": "0",
   "toughness": "0",
   "appearances": 1
  },
  {
   "name": "Galepowder Mage",
   "types": [
    "Creature"
   ],
   "sub_types": [
    "Kithkin",
    "Wizard"
   ],
   "cmc": 4,
   "image": "",
   "colors": [
    "W"
   ],
   "color_identity": [
    "W"
   ],
   "mana_cost": "{3}{W}",
   "url": "https://scryfall.com/card/clb/694/galepowder-mage?utm_source=api",
   "oracle_text": "Flying\nWhenever this creature attacks, exile another target creature. Return that card to the battlefield under its owner's control at the beginning of the next end step.",
   "power": "3",
   "toughness": "3",
   "appearances": 1
  },
  {
   "name": "Meadowboon",
   "types": [
    "Creature"
   ],
   "sub_types": [
    "Elemental"
   ],
   "cmc": 4,
   "image": "",
   "colors": [
    "W"
   ],
   "color_identity": [
    "W"
   ],
   "mana_cost": "{2}{W}{W}",
   "url": "https://scryfall.com/card/mma/22/meadowboon?utm_source=api",
   "oracle_text": "When this creature leaves the battlefield, put a +1/+1 counter on each creature target player controls.\nEvoke {3}{W} (You may cast this spell for its evoke cost. If you do, it's sacrificed when it enters.)",
   "power": "3",
   "toughness": "3",
   "appearances": 1
  },
  {
   "name": "Parallel Lives",
   "types": [
    "Enchantment"
   ],
   "cmc": 4,
   "image": "",
   "colors": [
    "G"
   ],
   "color_identity": [
    "G"
   ],
   "mana_cost": "{3}{G}",
   "url": "https://scryfall.com/card/isd/199/parallel-lives?utm_source=api",
   "oracle_text": "If an effect would create one or more tokens under your control, it creates twice that many of those tokens instead.",
   "appearances": 1
  },
  {
   "name": "Hardened Scales",
   "types": [
    "Enchantment"
   ],
   "cmc": 1,
   "image": "",
   "colors": [
    "G"
   ],
   "color_identity": [
    "G"
   ],
   "mana_cost": "{G}",
   "url": "https://scryfall.com/card/lcc/243/hardened-scales?utm_source=api",
   "oracle_text": "If one or more +1/+1 counters would be put on a creature you control, that many plus one +1/+1 counters are put on it instead.",
   "appearances": 1
  },
  {
   "name": "Saproling Migration",
   "types": [
    "Sorcery"
   ],
   "cmc": 2,
   "image": "",
   "colors": [
    "G"
   ],
   "color_identity": [
    "G"
   ],
   "mana_cost": "{1}{G}",
   "url": "https://scryfall.com/card/dom/178/saproling-migration?utm_source=api",
   "oracle_text": "Kicker {4} (You may pay an additional {4} as you cast this spell.)\nCreate two 1/1 green Saproling creature tokens. If this spell was kicked, create four of those tokens instead.",
   "appearances": 1
  },
  {
   "name": "Roaring Earth",
   "types": [
    "Enchantment"
   ],
   "cmc": 2,
   "image": "",
   "colors": [
    "G"
   ],
   "color_identity": [
    "G"
   ],
   "mana_cost": "{1}{G}",
   "url": "https://scryfall.com/card/neo/204/roaring-earth?utm_source=api",
   "oracle_text": "Landfall — Whenever a land you control enters, put a +1/+1 counter on target creature or Vehicle you control.\nChannel — {X}{G}{G}, Discard this card: Put X +1/+1 counters on target land you control. It becomes a 0/0 green Spirit creature with haste. It's still a land.",
   "appearances": 1
  },
  {
   "name": "Cloudgoat Ranger",
   "types": [
    "Creature"
   ],
   "sub_types": [
    "Giant",
    "Warrior",
    "Ranger"
   ],
   "cmc": 5,
   "image": "",
   "colors": [
    "W"
   ],
   "color_identity": [
    "W"
   ],
   "mana_cost": "{3}{W}{W}",
   "url": "https://scryfall.com/card/khc/21/cloudgoat-ranger?utm_source=api",
   "oracle_text": "When this creature enters, create three 1/1 white Kithkin Soldier creature tokens.\nTap three untapped Kithkin you control: This creature gets +2/+0 and gains flying until end of turn.",
   "power": "3",
   "toughness": "3",
   "appearances": 1
  },
  {
   "name": "Throne of the God-Pharaoh",
   "types": [
    "Legendary",
    "Artifact"
   ],
   "cmc": 2,
   "image": "",
   "colors": [],
   "color_identity": [],
   "mana_cost": "{2}",
   "url": "https://scryfall.com/card/akh/237/throne-of-the-god-pharaoh?utm_source=api",
   "oracle_text": "At the beginning of your end step, each opponent loses life equal to the number of tapped creatures you control.",
   "appearances": 1
  },
  {
   "name": "Soul Warden",
   "types": [
    "Creature"
   ],
   "sub_types": [
    "Human",
    "Cleric"
   ],
   "cmc": 1,
   "image": "",
   "colors": [
    "W"
   ],
   "color_identity": [
    "W"
   ],
   "mana_cost": "{W}",
   "url": "https://scryfall.com/card/mm3/24/soul-warden?utm_source=api",
   "oracle_text": "Whenever another creature enters, you gain 1 life.",
   "power": "1",
   "toughness": "1",
   "appearances": 1
  },
  {
   "name": "Panharmonicon",
   "types": [
    "Artifact"
   ],
   "cmc": 4,
   "image": "",
   "colors": [],
   "color_identity": [],
   "mana_cost": "{4}",
   "url": "https://scryfall.com/card/2x2/310/panharmonicon?utm_source=api",
   "oracle_text": "If an artifact or creature entering causes a triggered ability of a permanent you control to trigger, that ability triggers an additional time.",
   "appearances": 1
  },
  {
   "name": "Hunting Triad",
   "types": [
    "Kindred",
    "Sorcery"
   ],
   "sub_types": [
    "Elf"
   ],
   "cmc": 4,
   "image": "",
   "colors": [
    "G"
   ],
   "color_identity": [
    "G"
   ],
   "mana_cost": "{3}{G}",
   "url": "https://scryfall.com/card/cma/116/hunting-triad?utm_source=api",
   "oracle_text": "Create three 1/1 green Elf Warrior creature tokens.\nReinforce 3—{3}{G} ({3}{G}, Discard this card: Put three +1/+1 counters on target creature.)",
   "appearances": 1
  },
  {
   "name": "Pollenbright Druid",
   "types": [
    "Creature"
   ],
   "sub_types": [
    "Elf",
    "Druid"
   ],
   "cmc": 2,
   "image": "",
   "colors": [
    "G"
   ],
   "color_identity": [
    "G"
   ],
   "mana_cost": "{1}{G}",
   "url": "https://scryfall.com/card/cmm/312/pollenbright-druid?utm_source=api",
   "oracle_text": "When this creature enters, choose one —\n• Put a +1/+1 counter on target creature.\n• Proliferate. (Choose any number of permanents and/or players, then give each another counter of each kind already there.)",
   "power": "1",
   "toughness": "1",
   "appearances": 1
  },
  {
   "name": "Glass Casket",
   "types": [
    "Artifact"
   ],
   "cmc": 2,
   "image": "",
   "colors": [
    "W"
   ],
   "color_identity": [
    "W"
   ],
   "mana_cost": "{1}{W}",
   "url": "https://scryfall.com/card/woe/16/glass-casket?utm_source=api",
   "oracle_text": "When this artifact enters, exile target creature an opponent controls with mana value 3 or less until this artifact leaves the battlefield.",
   "appearances": 1
  },
  {
   "name": "Windswept Heath",
   "types": [
    "Land"
   ],
   "cmc": 0,
   "image": "",
   "colors": [],
   "color_identity": [],
   "mana_cost": "",
   "url": "https://scryfall.com/card/mh3/235/windswept-heath?utm_source=api",
   "oracle_text": "{T}, Pay 1 life, Sacrifice this land: Search your library for a Forest or Plains card, put it onto the battlefield, then shuffle.",
   "appearances": 1
  },
  {
   "name": "Scattered Groves",
   "types": [
    "Land"
   ],
   "sub_types": [
    "Forest",
    "Plains"
   ],
   "cmc": 0,
   "image": "",
   "colors": [],
   "color_identity": [
    "G",
    "W"
   ],
   "mana_cost": "",
   "url": "https://scryfall.com/card/otc/315/scattered-groves?utm_source=api",
   "oracle_text": "({T}: Add {G} or {W}.)\nThis land enters tapped.\nCycling {2} ({2}, Discard this card: Draw a card.)",
   "appearances": 1
  },
  {
   "name": "Mistmeadow Skulk",
   "types": [
    "Creature"
   ],
   "sub_types": [
    "Kithkin",
    "Rogue"
   ],
   "cmc": 2,
   "image": "",
   "colors": [
    "W"
   ],
   "color_identity": [
    "W"
   ],
   "mana_cost": "{1}{W}",
   "url": "https://scryfall.com/card/otc/84/mistmeadow-skulk?utm_source=api",
   "oracle_text": "Lifelink, protection from mana value 3 or greater",
   "power": "1",
   "toughness": "1",
   "appearances": 1
  },
  {
   "name": "Blade of the Bloodchief",
   "types": [
    "Artifact"
   ],
   "sub_types": [
    "Equipment"
   ],
   "cmc": 1,
   "image": "",
   "colors": [],
   "color_identity": [],
   "mana_cost": "{1}",
   "url": "https://scryfall.com/card/lcc/300/blade-of-the-bloodchief?utm_source=api",
   "oracle_text": "Whenever a creature dies, put a +1/+1 counter on equipped creature. If equipped creature is a Vampire, put two +1/+1 counters on it instead.\nEquip {1}",
   "appearances": 1
  },
  {
   "name": "Kor Sanctifiers",
   "types": [
    "Creature"
   ],
   "sub_types": [
    "Kor",
    "Cleric"
   ],
   "cmc": 3,
   "image": "",
   "colors": [
    "W"
   ],
   "color_identity": [
    "W"
   ],
   "mana_cost": "{2}{W}",
   "url": "https://scryfall.com/card/c15/73/kor-sanctifiers?utm_source=api",
   "oracle_text": "Kicker {W} (You may pay an additional {W} as you cast this spell.)\nWhen this creature enters, if it was kicked, destroy target artifact or enchantment.",
   "power": "2",
   "toughness": "3",
   "appearances": 1
  },
  {
   "name": "Werefox Bodyguard",
   "types": [
    "Creature"
   ],
   "sub_types": [
    "Elf",
    "Fox",
    "Knight"
   ],
   "cmc": 3,
   "image": "",
   "colors": [
    "W"
   ],
   "color_identity": [
    "W"
   ],
   "mana_cost": "{1}{W}{W}",
   "url": "https://scryfall.com/card/woe/39/werefox-bodyguard?utm_source=api",
   "oracle_text": "Flash\nWhen this creature enters, exile up to one other target non-Fox creature until this creature leaves the battlefield.\n{1}{W}, Sacrifice this creature: You gain 2 life.",
   "power": "2",
   "toughness": "2",
   "appearances": 1
  },
  {
   "name": "Reprieve",
   "types": [
    "Instant"
   ],
   "cmc": 2,
   "image": "",
   "colors": [
    "W"
   ],
   "color_identity": [
    "W"
   ],
   "mana_cost": "{1}{W}",
   "url": "https://scryfall.com/card/ltr/26/reprieve?utm_source=api",
   "oracle_text": "Return target spell to its owner's hand.\nDraw a card.",
   "appearances": 1
  },
  {
   "name": "Spirited Companion",
   "types": [
    "Enchantment",
    "Creature"
   ],
   "sub_types": [
    "Dog"
   ],
   "cmc": 2,
   "image": "",
   "colors": [
    "W"
   ],
   "color_identity": [
    "W"
   ],
   "mana_cost": "{1}{W}",
   "url": "https://scryfall.com/card/cmm/838/spirited-companion?utm_source=api",
   "oracle_text": "When this creature enters, draw a card.",
   "power": "1",
   "toughness": "1",
   "appearances": 1
  },
  {
   "name": "Sparring Construct",
   "types": [
    "Artifact",
    "Creature"
   ],
   "sub_types": [
    "Construct"
   ],
   "cmc": 1,
   "image": "",
   "colors": [],
   "color_identity": [],
   "mana_cost": "{1}",
   "url": "https://scryfall.com/card/dom/232/sparring-construct?utm_source=api",
   "oracle_text": "When this creature dies, put a +1/+1 counter on target creature you control.",
   "power": "1",
   "toughness": "1",
   "appearances": 1
  },
  {
   "name": "Plains",
   "types": [
    "Basic",
    "Land"
   ],
   "sub_types": [
    "Plains"
   ],
   "cmc": 0,
   "image": "",
   "colors": [],
   "color_identity": [
    "W"
   ],
   "mana_cost": "",
   "url": "https://scryfall.com/card/tla/282/plains?utm_source=api",
   "oracle_text": "({T}: Add {W}.)",
   "appearances": 1
  },
  {
   "name": "Plains",
   "types": [
    "Basic",
    "Land"
   ],
   "sub_types": [
    "Plains"
   ],
   "cmc": 0,
   "image": "",
   "colors": [],
   "color_identity": [
    "W"
   ],
   "mana_cost": "",
   "url": "https://scryfall.com/card/tla/282/plains?utm_source=api",
   "oracle_text": "({T}: Add {W}.)",
   "appearances": 1
  },
  {
   "name": "Plains",
   "types": [
    "Basic",
    "Land"
   ],
   "sub_types": [
    "Plains"
   ],
   "cmc": 0,
   "image": "",
   "colors": [],
   "color_identity": [
    "W"
   ],
   "mana_cost": "",
   "url": "https://scryfall.com/card/tla/282/plains?utm_source=api",
   "oracle_text": "({T}: Add {W}.)",
   "appearances": 1
  },
  {
   "name": "Plains",
   "types": [
    "Basic",
    "Land"
   ],
   "sub_types": [
    "Plains"
   ],
   "cmc": 0,
   "image": "",
   "colors": [],
   "color_identity": [
    "W"
   ],
   "mana_cost": "",
   "url": "https://scryfall.com/card/tla/282/plains?utm_source=api",
   "oracle_text": "({T}: Add {W}.)",
   "appearances": 1
  },
  {
   "name": "Plains",
   "types": [
    "Basic",
    "Land"
   ],
   "sub_types": [
    "Plains"
   ],
   "cmc": 0,
   "image": "",
   "colors": [],
   "color_identity": [
    "W"
   ],
   "mana_cost": "",
   "url": "https://scryfall.com/card/tla/282/plains?utm_source=api",
   "oracle_text": "({T}: Add {W}.)",
   "appearances": 1
  },
  {
   "name": "Plains",
   "types": [
    "Basic",
    "Land"
   ],
   "sub_types": [
    "Plains"
   ],
   "cmc": 0,
   "image": "",
   "colors": [],
   "color_identity": [
    "W"
   ],
   "mana_cost": "",
   "url": "https://scryfall.com/card/tla/282/plains?utm_source=api",
   "oracle_text": "({T}: Add {W}.)",
   "appearances": 1
  },
  {
   "name": "Plains",
   "types": [
    "Basic",
    "Land"
   ],
   "sub_types": [
    "Plains"
   ],
   "cmc": 0,
   "image": "",
   "colors": [],
   "color_identity": [
    "W"
   ],
   "mana_cost": "",
   "url": "https://scryfall.com/card/tla/282/plains?utm_source=api",
   "oracle_text": "({T}: Add {W}.)",
   "appearances": 1
  },
  {
   "name": "Plains",
   "types": [
    "Basic",
    "Land"
   ],
   "sub_types": [
    "Plains"
   ],
   "cmc": 0,
   "image": "",
   "colors": [],
   "color_identity": [
    "W"
   ],
   "mana_cost": "",
   "url": "https://scryfall.com/card/tla/282/plains?utm_source=api",
   "oracle_text": "({T}: Add {W}.)",
   "appearances": 1
  },
  {
   "name": "Forest",
   "types": [
    "Basic",
    "Land"
   ],
   "sub_types": [
    "Forest"
   ],
   "cmc": 0,
   "image": "",
   "colors": [],
   "color_identity": [
    "G"
   ],
   "mana_cost": "",
   "url": "https://scryfall.com/card/tla/286/forest?utm_source=api",
   "oracle_text": "({T}: Add {G}.)",
   "appearances": 1
  },
  {
   "name": "Forest",
   "types": [
    "Basic",
    "Land"
   ],
   "sub_types": [
    "Forest"
   ],
   "cmc": 0,
   "image": "",
   "colors": [],
   "color_identity": [
    "G"
   ],
   "mana_cost": "",
   "url": "https://scryfall.com/card/tla/286/forest?utm_source=api",
   "oracle_text": "({T}: Add {G}.)",
   "appearances": 1
  },
  {
   "name": "Forest",
   "types": [
    "Basic",
    "Land"
   ],
   "sub_types": [
    "Forest"
   ],
   "cmc": 0,
   "image": "",
   "colors": [],
   "color_identity": [
    "G"
   ],
   "mana_cost": "",
   "url": "https://scryfall.com/card/tla/286/forest?utm_source=api",
   "oracle_text": "({T}: Add {G}.)",
   "appearances": 1
  },
  {
   "name": "Forest",
   "types": [
    "Basic",
    "Land"
   ],
   "sub_types": [
    "Forest"
   ],
   "cmc": 0,
   "image": "",
   "colors": [],
   "color_identity": [
    "G"
   ],
   "mana_cost": "",
   "url": "https://scryfall.com/card/tla/286/forest?utm_source=api",
   "oracle_text": "({T}: Add {G}.)",
   "appearances": 1
  },
  {
   "name": "Forest",
   "types": [
    "Basic",
    "Land"
   ],
   "sub_types": [
    "Forest"
   ],
   "cmc": 0,
   "image": "",
   "colors": [],
   "color_identity": [
    "G"
   ],
   "mana_cost": "",
   "url": "https://scryfall.com/card/tla/286/forest?utm_source=api",
   "oracle_text": "({T}: Add {G}.)",
   "appearances": 1
  },
  {
   "name": "Forest",
   "types": [
    "Basic",
    "Land"
   ],
   "sub_types": [
    "Forest"
   ],
   "cmc": 0,
   "image": "",
   "colors": [],
   "color_identity": [
    "G"
   ],
   "mana_cost": "",
   "url": "https://scryfall.com/card/tla/286/forest?utm_source=api",
   "oracle_text": "({T}: Add {G}.)",
   "appearances": 1
  },
  {
   "name": "Forest",
   "types": [
    "Basic",
    "Land"
   ],
   "sub_types": [
    "Forest"
   ],
   "cmc": 0,
   "image": "",
   "colors": [],
   "color_identity": [
    "G"
   ],
   "mana_cost": "",
   "url": "https://scryfall.com/card/tla/286/forest?utm_source=api",
   "oracle_text": "({T}: Add {G}.)",
   "appearances": 1
  }
 ],
 "sideboard": [
  {
   "name": "Hedron Crab",
   "types": [
    "Creature"
   ],
   "sub_types": [
    "Crab"
   ],
   "cmc": 1,
   "image": "",
   "colors": [
    "U"
   ],
   "color_identity": [
    "U"
   ],
   "mana_cost": "{U}",
   "url": "https://scryfall.com/card/tdc/155/hedron-crab?utm_source=api",
   "oracle_text": "Landfall — Whenever a land you control enters, target player mills three cards. (They put the top three cards of their library into their graveyard.)",
   "power": "0",
   "toughness": "2"
  },
  {
   "name": "Flux Channeler",
   "types": [
    "Creature"
   ],
   "sub_types": [
    "Human",
    "Wizard"
   ],
   "cmc": 3,
   "image": "",
   "colors": [
    "U"
   ],
   "color_identity": [
    "U"
   ],
   "mana_cost": "{2}{U}",
   "url": "https://scryfall.com/card/cmm/847/flux-channeler?utm_source=api",
   "oracle_text": "Whenever you cast a noncreature spell, proliferate. (Choose any number of permanents and/or players, then give each another counter of each kind already there.)",
   "power": "2",
   "toughness": "2"
  },
  {
   "name": "Domri's Ambush",
   "types": [
    "Sorcery"
   ],
   "cmc": 2,
   "image": "",
   "colors": [
    "G",
    "R"
   ],
   "color_identity": [
    "G",
    "R"
   ],
   "mana_cost": "{R}{G}",
   "url": "https://scryfall.com/card/war/192/domris-ambush?utm_source=api",
   "oracle_text": "Put a +1/+1 counter on target creature you control. Then that creature deals damage equal to its power to target creature or planeswalker you don't control."
  },
  {
   "name": "Mental Note",
   "types": [
    "Instant"
   ],
   "cmc": 1,
   "image": "",
   "colors": [
    "U"
   ],
   "color_identity": [
    "U"
   ],
   "mana_cost": "{U}",
   "url": "https://scryfall.com/card/jud/46/mental-note?utm_source=api",
   "oracle_text": "Mill two cards.\nDraw a card."
  },
  {
   "name": "Rootbound Crag",
   "types": [
    "Land"
   ],
   "cmc": 0,
   "image": "",
   "colors": [],
   "color_identity": [
    "G",
    "R"
   ],
   "mana_cost": "",
   "url": "https://scryfall.com/card/tdc/388/rootbound-crag?utm_source=api",
   "oracle_text": "This land enters tapped unless you control a Mountain or a Forest.\n{T}: Add {R} or {G}."
  },
  {
   "name": "Titania, Protector of Argoth",
   "types": [
    "Legendary",
    "Creature"
   ],
   "sub_types": [
    "Elemental"
   ],
   "cmc": 5,
   "image": "",
   "colors": [
    "G"
   ],
   "color_identity": [
    "G"
   ],
   "mana_cost": "{3}{G}{G}",
   "url": "https://scryfall.com/card/eoc/111/titania-protector-of-argoth?utm_source=api",
   "oracle_text": "When Titania enters, return target land card from your graveyard to the battlefield.\nWhenever a land you control is put into a graveyard from the battlefield, create a 5/3 green Elemental creature token.",
   "power": "5",
   "toughness": "3"
  },
  {
   "name": "Cauldron of Souls",
   "types": [
    "Artifact"
   ],
   "cmc": 5,
   "image": "",
   "colors": [],
   "color_identity": [],
   "mana_cost": "{5}",
   "url": "https://scryfall.com/card/cm2/180/cauldron-of-souls?utm_source=api",
   "oracle_text": "{T}: Choose any number of target creatures. Each of those creatures gains persist until end of turn. (When it dies, if it had no -1/-1 counters on it, return it to the battlefield under its owner's control with a -1/-1 counter on it.)"
  },
  {
   "name": "Marshal's Anthem",
   "types": [
    "Enchantment"
   ],
   "cmc": 4,
   "image": "",
   "colors": [
    "W"
   ],
   "color_identity": [
    "W"
   ],
   "mana_cost": "{2}{W}{W}",
   "url": "https://scryfall.com/card/otc/82/marshals-anthem?utm_source=api",
   "oracle_text": "Multikicker {1}{W} (You may pay an additional {1}{W} any number of times as you cast this spell.)\nCreatures you control get +1/+1.\nWhen this enchantment enters, return up to X target creature cards from your graveyard to the battlefield, where X is the number of times this enchantment was kicked."
  },
  {
   "name": "Wilderness Reclamation",
   "types": [
    "Enchantment"
   ],
   "cmc": 4,
   "image": "",
   "colors": [
    "G"
   ],
   "color_identity": [
    "G"
   ],
   "mana_cost": "{3}{G}",
   "url": "https://scryfall.com/card/dsc/205/wilderness-reclamation?utm_source=api",
   "oracle_text": "At the beginning of your end step, untap all lands you control."
  },
  {
   "name": "Angelic Intervention",
   "types": [
    "Instant"
   ],
   "cmc": 2,
   "image": "",
   "colors": [
    "W"
   ],
   "color_identity": [
    "W"
   ],
   "mana_cost": "{1}{W}",
   "url": "https://scryfall.com/card/mom/5/angelic-intervention?utm_source=api",
   "oracle_text": "Target creature or planeswalker you control gains protection from colorless or from the color of your choice until end of turn. If it's a creature, put a +1/+1 counter on it. (It can't be blocked, targeted, dealt damage, enchanted, or equipped by anything with that quality.)"
  },
  {
   "name": "Jinxed Idol",
   "types": [
    "Artifact"
   ],
   "cmc": 2,
   "image": "",
   "colors": [],
   "color_identity": [],
   "mana_cost": "{2}",
   "url": "https://scryfall.com/card/tpr/224/jinxed-idol?utm_source=api",
   "oracle_text": "At the beginning of your upkeep, this artifact deals 2 damage to you.\nSacrifice a creature: Target opponent gains control of this artifact."
  },
  {
   "name": "Chromatic Sphere",
   "types": [
    "Artifact"
   ],
   "cmc": 1,
   "image": "",
   "colors": [],
   "color_identity": [],
   "mana_cost": "{1}",
   "url": "https://scryfall.com/card/jmp/462/chromatic-sphere?utm_source=api",
   "oracle_text": "{1}, {T}, Sacrifice this artifact: Add one mana of any color. Draw a card."
  },
  {
   "name": "Kor Skyfisher",
   "types": [
    "Creature"
   ],
   "sub_types": [
    "Kor",
    "Soldier"
   ],
   "cmc": 2,
   "image": "",
   "colors": [
    "W"
   ],
   "color_identity": [
    "W"
   ],
   "mana_cost": "{1}{W}",
   "url": "https://scryfall.com/card/mm3/11/kor-skyfisher?utm_source=api",
   "oracle_text": "Flying\nWhen this creature enters, return a permanent you control to its owner's hand.",
   "power": "2",
   "toughness": "3"
  },
  {
   "name": "Worm Harvest",
   "types": [
    "Sorcery"
   ],
   "cmc": 5,
   "image": "",
   "colors": [
    "B",
    "G"
   ],
   "color_identity": [
    "B",
    "G"
   ],
   "mana_cost": "{2}{B/G}{B/G}{B/G}",
   "url": "https://scryfall.com/card/c18/194/worm-harvest?utm_source=api",
   "oracle_text": "Create a 1/1 black and green Worm creature token for each land card in your graveyard.\nRetrace (You may cast this card from your graveyard by discarding a land card in addition to paying its other costs.)"
  },
  {
   "name": "Eidolon of Obstruction",
   "types": [
    "Enchantment",
    "Creature"
   ],
   "sub_types": [
    "Spirit"
   ],
   "cmc": 2,
   "image": "",
   "colors": [
    "W"
   ],
   "color_identity": [
    "W"
   ],
   "mana_cost": "{1}{W}",
   "url": "https://scryfall.com/card/thb/12/eidolon-of-obstruction?utm_source=api",
   "oracle_text": "First strike\nLoyalty abilities of planeswalkers your opponents control cost {1} more to activate.",
   "power": "2",
   "toughness": "1"
  },
  {
   "name": "Kor Duelist",
   "types": [
    "Creature"
   ],
   "sub_types": [
    "Kor",
    "Soldier"
   ],
   "cmc": 1,
   "image": "",
   "colors": [
    "W"
   ],
   "color_identity": [
    "W"
   ],
   "mana_cost": "{W}",
   "url": "https://scryfall.com/card/mm2/22/kor-duelist?utm_source=api",
   "oracle_text": "As long as this creature is equipped, it has double strike. (It deals both first-strike and regular combat damage.)",
   "power": "1",
   "toughness": "1"
  },
  {
   "name": "Multani, Yavimaya's Avatar",
   "types": [
    "Legendary",
    "Creature"
   ],
   "sub_types": [
    "Elemental",
    "Avatar"
   ],
   "cmc": 6,
   "image": "",
   "colors": [
    "G"
   ],
   "color_identity": [
    "G"
   ],
   "mana_cost": "{4}{G}{G}",
   "url": "https://scryfall.com/card/eoc/100/multani-yavimayas-avatar?utm_source=api",
   "oracle_text": "Reach, trample\nMultani gets +1/+1 for each land you control and each land card in your graveyard.\n{1}{G}, Return two lands you control to their owner's hand: Return this card from your graveyard to your hand.",
   "power": "0",
   "toughness": "0"
  },
  {
   "name": "Oracle of Mul Daya",
   "types": [
    "Creature"
   ],
   "sub_types": [
    "Elf",
    "Shaman"
   ],
   "cmc": 4,
   "image": "",
   "colors": [
    "G"
   ],
   "color_identity": [
    "G"
   ],
   "mana_cost": "{3}{G}",
   "url": "https://scryfall.com/card/eoc/102/oracle-of-mul-daya?utm_source=api",
   "oracle_text": "You may play an additional land on each of your turns.\nPlay with the top card of your library revealed.\nYou may play lands from the top of your library.",
   "power": "2",
   "toughness": "2"
  },
  {
   "name": "Harrow",
   "types": [
    "Instant"
   ],
   "cmc": 3,
   "image": "",
   "colors": [
    "G"
   ],
   "color_identity": [
    "G"
   ],
   "mana_cost": "{2}{G}",
   "url": "https://scryfall.com/card/eoc/98/harrow?utm_source=api",
   "oracle_text": "As an additional cost to cast this spell, sacrifice a land.\nSearch your library for up to two basic land cards, put them onto the battlefield, then shuffle."
  }
 ]
}