{
 "metadata": {
  "path": "data/polyverse/2024-03-31/xander.json",
  "draft_id": "2024-03-31",
  "source_files": [
   "xander.txt"
  ]
 },
 "labels": [
  "midrange",
  "sacrifice",
  "token"
 ],
 "player": "xander",
 "date": "2024-03-31",
 "games": [
  {
   "opponent": "cara",
   "winner": "xander"
  },
  {
   "opponent": "cara",
   "winner": "cara"
  },
  {
   "opponent": "cara",
   "winner": "cara"
  },
  {
   "opponent": "jen",
   "winner": "xander"
  },
  {
   "opponent": "jen",
   "winner": "xander"
  },
  {
   "opponent": "paul",
   "winner": "xander"
  },
  {
   "opponent": "paul",
   "winner": "xander"
  },
  {
   "opponent": "paul",
   "winner": "paul"
  }
 ],
 "matches": [
  {
   "opponent": "cara",
   "winner": "cara"
  },
  {
   "opponent": "jen",
   "winner": "xander"
  },
  {
   "opponent": "paul",
   "winner": "xander"
  }
 ],
 "mainboard": [
  {
   "name": "Twinshot Sniper",
   "types": [
    "Artifact",
    "Creature"
   ],
   "sub_types": [
    "Goblin",
    "Archer"
   ],
   "cmc": 4,
   "image": "",
   "colors": [
    "R"
   ],
   "color_identity": [
    "R"
   ],
   "mana_cost": "{3}{R}",
   "url": "https://scryfall.com/card/neo/168/twinshot-sniper?utm_source=api",
   "oracle_text": "Reach\nWhen this creature enters, it deals 2 damage to any target.\nChannel — {1}{R}, Discard this card: It deals 2 damage to any target.",
   "power": "2",
   "toughness": "3",
   "appearances": 1
  },
  {
   "name": "Mayhem Devil",
   "types": [
    "Creature"
   ],
   "sub_types": [
    "Devil"
   ],
   "cmc": 3,
   "image": "",
   "colors": [
    "B",
    "R"
   ],
   "color_identity": [
    "B",
    "R"
   ],
   "mana_cost": "{1}{B}{R}",
   "url": "https://scryfall.com/card/eoc/121/mayhem-devil?utm_source=api",
   "oracle_text": "Whenever a player sacrifices a permanent, this creature deals 1 damage to any target.",
   "power": "3",
   "toughness": "3",
   "appearances": 1
  },
  {
   "name": "Prismatic Ending",
   "types": [
    "Sorcery"
   ],
   "cmc": 1,
   "image": "",
   "colors": [
    "W"
   ],
   "color_identity": [
    "W"
   ],
   "mana_cost": "{X}{W}",
   "url": "https://scryfall.com/card/mh2/25/prismatic-ending?utm_source=api",
   "oracle_text": "Converge — Exile target nonland permanent if its mana value is less than or equal to the number of colors of mana spent to cast this spell.",
   "appearances": 1
  },
  {
   "name": "Aether Spellbomb",
   "types": [
    "Artifact"
   ],
   "cmc": 1,
   "image": "",
   "colors": [],
   "color_identity": [
    "U"
   ],
   "mana_cost": "{1}",
   "url": "https://scryfall.com/card/jmp/456/aether-spellbomb?utm_source=api",
   "oracle_text": "{U}, Sacrifice this artifact: Return target creature to its owner's hand.\n{1}, Sacrifice this artifact: Draw a card.",
   "appearances": 1
  },
  {
   "name": "Reveillark",
   "types": [
    "Creature"
   ],
   "sub_types": [
    "Elemental"
   ],
   "cmc": 5,
   "image": "",
   "colors": [
    "W"
   ],
   "color_identity": [
    "W"
   ],
   "mana_cost": "{4}{W}",
   "url": "https://scryfall.com/card/2x2/26/reveillark?utm_source=api",
   "oracle_text": "Flying\nWhen this creature leaves the battlefield, return up to two target creature cards with power 2 or less from your graveyard to the battlefield.\nEvoke {5}{W} (You may cast this spell for its evoke cost. If you do, it's sacrificed when it enters.)",
   "power": "4",
   "toughness": "3",
   "appearances": 1
  },
  {
   "name": "Battlefield Forge",
   "types": [
    "Land"
   ],
   "cmc": 0,
   "image": "",
   "colors": [],
   "color_identity": [
    "R",
    "W"
   ],
   "mana_cost": "",
   "url": "https://scryfall.com/card/eoc/58/battlefield-forge?utm_source=api",
   "oracle_text": "{T}: Add {C}.\n{T}: Add {R} or {W}. This land deals 1 damage to you.",
   "appearances": 1
  },
  {
   "name": "Sacred Foundry",
   "types": [
    "Land"
   ],
   "sub_types": [
    "Mountain",
    "Plains"
   ],
   "cmc": 0,
   "image": "",
   "colors": [],
   "color_identity": [
    "R",
    "W"
   ],
   "mana_cost": "",
   "url": "https://scryfall.com/card/eoe/256/sacred-foundry?utm_source=api",
   "oracle_text": "({T}: Add {R} or {W}.)\nAs this land enters, you may pay 2 life. If you don't, it enters tapped.",
   "appearances": 1
  },
  {
   "name": "Canyon Slough",
   "types": [
    "Land"
   ],
   "sub_types": [
    "Swamp",
    "Mountain"
   ],
   "cmc": 0,
   "image": "",
   "colors": [],
   "color_identity": [
    "B",
    "R"
   ],
   "mana_cost": "",
   "url": "https://scryfall.com/card/eoc/152/canyon-slough?utm_source=api",
   "oracle_text": "({T}: Add {B} or {R}.)\nThis land enters tapped.\nCycling {2} ({2}, Discard this card: Draw a card.)",
   "appearances": 1
  },
  {
   "name": "Sparring Construct",
   "types": [
    "Artifact",
    "Creature"
   ],
   "sub_types": [
    "Construct"
   ],
   "cmc": 1,
   "image": "",
   "colors": [],
   "color_identity": [],
   "mana_cost": "{1}",
   "url": "https://scryfall.com/card/dom/232/sparring-construct?utm_source=api",
   "oracle_text": "When this creature dies, put a +1/+1 counter on target creature you control.",
   "power": "1",
   "toughness": "1",
   "appearances": 1
  },
  {
   "name": "Jinxed Idol",
   "types": [
    "Artifact"
   ],
   "cmc": 2,
   "image": "",
   "colors": [],
   "color_identity": [],
   "mana_cost": "{2}",
   "url": "https://scryfall.com/card/tpr/224/jinxed-idol?utm_source=api",
   "oracle_text": "At the beginning of your upkeep, this artifact deals 2 damage to you.\nSacrifice a creature: Target opponent gains control of this artifact.",
   "appearances": 1
  },
  {
   "name": "Goblin Arsonist",
   "types": [
    "Creature"
   ],
   "sub_types": [
    "Goblin",
    "Shaman"
   ],
   "cmc": 1,
   "image": "",
   "colors": [
    "R"
   ],
   "color_identity": [
    "R"
   ],
   "mana_cost": "{R}",
   "url": "https://scryfall.com/card/m21/147/goblin-arsonist?utm_source=api",
   "oracle_text": "When this creature dies, you may have it deal 1 damage to any target.",
   "power": "1",
   "toughness": "1",
   "appearances": 1
  },
  {
   "name": "Fetid Pools",
   "types": [
    "Land"
   ],
   "sub_types": [
    "Island",
    "Swamp"
   ],
   "cmc": 0,
   "image": "",
   "colors": [],
   "color_identity": [
    "B",
    "U"
   ],
   "mana_cost": "",
   "url": "https://scryfall.com/card/tdc/363/fetid-pools?utm_source=api",
   "oracle_text": "({T}: Add {U} or {B}.)\nThis land enters tapped.\nCycling {2} ({2}, Discard this card: Draw a card.)",
   "appearances": 1
  },
  {
   "name": "Lion Sash",
   "types": [
    "Artifact",
    "Creature"
   ],
   "sub_types": [
    "Equipment",
    "Cat"
   ],
   "cmc": 2,
   "image": "",
   "colors": [
    "W"
   ],
   "color_identity": [
    "W"
   ],
   "mana_cost": "{1}{W}",
   "url": "https://scryfall.com/card/neo/26/lion-sash?utm_source=api",
   "oracle_text": "{W}: Exile target card from a graveyard. If it was a permanent card, put a +1/+1 counter on this permanent.\nEquipped creature gets +1/+1 for each +1/+1 counter on this Equipment.\nReconfigure {2} ({2}: Attach to target creature you control; or unattach from a creature. Reconfigure only as a sorcery. While attached, this isn't a creature.)",
   "power": "1",
   "toughness": "1",
   "appearances": 1
  },
  {
   "name": "Cruel Celebrant",
   "types": [
    "Creature"
   ],
   "sub_types": [
    "Vampire"
   ],
   "cmc": 2,
   "image": "",
   "colors": [
    "B",
    "W"
   ],
   "color_identity": [
    "B",
    "W"
   ],
   "mana_cost": "{W}{B}",
   "url": "https://scryfall.com/card/lcc/267/cruel-celebrant?utm_source=api",
   "oracle_text": "Whenever this creature or another creature or planeswalker you control dies, each opponent loses 1 life and you gain 1 life.",
   "power": "1",
   "toughness": "2",
   "appearances": 1
  },
  {
   "name": "Bloodstained Mire",
   "types": [
    "Land"
   ],
   "cmc": 0,
   "image": "",
   "colors": [],
   "color_identity": [],
   "mana_cost": "",
   "url": "https://scryfall.com/card/mh3/216/bloodstained-mire?utm_source=api",
   "oracle_text": "{T}, Pay 1 life, Sacrifice this land: Search your library for a Swamp or Mountain card, put it onto the battlefield, then shuffle.",
   "appearances": 1
  },
  {
   "name": "Goblin Bombardment",
   "types": [
    "Enchantment"
   ],
   "cmc": 2,
   "image": "",
   "colors": [
    "R"
   ],
   "color_identity": [
    "R"
   ],
   "mana_cost": "{1}{R}",
   "url": "https://scryfall.com/card/mh2/279/goblin-bombardment?utm_source=api",
   "oracle_text": "Sacrifice a creature: This enchantment deals 1 damage to any target.",
   "appearances": 1
  },
  {
   "name": "Cut Down",
   "types": [
    "Instant"
   ],
   "cmc": 1,
   "image": "",
   "colors": [
    "B"
   ],
   "color_identity": [
    "B"
   ],
   "mana_cost": "{B}",
   "url": "https://scryfall.com/card/dmu/89/cut-down?utm_source=api",
   "oracle_text": "Destroy target creature with total power and toughness 5 or less.",
   "appearances": 1
  },
  {
   "name": "Oust",
   "types": [
    "Sorcery"
   ],
   "cmc": 1,
   "image": "",
   "colors": [
    "W"
   ],
   "color_identity": [
    "W"
   ],
   "mana_cost": "{W}",
   "url": "https://scryfall.com/card/clu/67/oust?utm_source=api",
   "oracle_text": "Put target creature into its owner's library second from the top. Its controller gains 3 life.",
   "appearances": 1
  },
  {
   "name": "Godless Shrine",
   "types": [
    "Land"
   ],
   "sub_types": [
    "Plains",
    "Swamp"
   ],
   "cmc": 0,
   "image": "",
   "colors": [],
   "color_identity": [
    "B",
    "W"
   ],
   "mana_cost": "",
   "url": "https://scryfall.com/card/eoe/254/godless-shrine?utm_source=api",
   "oracle_text": "({T}: Add {W} or {B}.)\nAs this land enters, you may pay 2 life. If you don't, it enters tapped.",
   "appearances": 1
  },
  {
   "name": "Clarion Spirit",
   "types": [
    "Creature"
   ],
   "sub_types": [
    "Spirit"
   ],
   "cmc": 2,
   "image": "",
   "colors": [
    "W"
   ],
   "color_identity": [
    "W"
   ],
   "mana_cost": "{1}{W}",
   "url": "https://scryfall.com/card/khm/6/clarion-spirit?utm_source=api",
   "oracle_text": "Whenever you cast your second spell each turn, create a 1/1 white Spirit creature token with flying.",
   "power": "2",
   "toughness": "2",
   "appearances": 1
  },
  {
   "name": "Mogg War Marshal",
   "types": [
    "Creature"
   ],
   "sub_types": [
    "Goblin",
    "Warrior"
   ],
   "cmc": 2,
   "image": "",
   "colors": [
    "R"
   ],
   "color_identity": [
    "R"
   ],
   "mana_cost": "{1}{R}",
   "url": "https://scryfall.com/card/dmr/131/mogg-war-marshal?utm_source=api",
   "oracle_text": "Echo {1}{R} (At the beginning of your upkeep, if this came under your control since the beginning of your last upkeep, sacrifice it unless you pay its echo cost.)\nWhen this creature enters or dies, create a 1/1 red Goblin creature token.",
   "power": "1",
   "toughness": "1",
   "appearances": 1
  },
  {
   "name": "Irrigated Farmland",
   "types": [
    "Land"
   ],
   "sub_types": [
    "Plains",
    "Island"
   ],
   "cmc": 0,
   "image": "",
   "colors": [],
   "color_identity": [
    "U",
    "W"
   ],
   "mana_cost": "",
   "url": "https://scryfall.com/card/eoc/162/irrigated-farmland?utm_source=api",
   "oracle_text": "({T}: Add {W} or {U}.)\nThis land enters tapped.\nCycling {2} ({2}, Discard this card: Draw a card.)",
   "appearances": 1
  },
  {
   "name": "Fiery Islet",
   "types": [
    "Land"
   ],
   "cmc": 0,
   "image": "",
   "colors": [],
   "color_identity": [
    "R",
    "U"
   ],
   "mana_cost": "",
   "url": "https://scryfall.com/card/mh1/238/fiery-islet?utm_source=api",
   "oracle_text": "{T}, Pay 1 life: Add {U} or {R}.\n{1}, {T}, Sacrifice this land: Draw a card.",
   "appearances": 1
  },
  {
   "name": "Flooded Strand",
   "types": [
    "Land"
   ],
   "cmc": 0,
   "image": "",
   "colors": [],
   "color_identity": [],
   "mana_cost": "",
   "url": "https://scryfall.com/card/mh3/220/flooded-strand?utm_source=api",
   "oracle_text": "{T}, Pay 1 life, Sacrifice this land: Search your library for a Plains or Island card, put it onto the battlefield, then shuffle.",
   "appearances": 1
  },
  {
   "name": "Sevinne's Reclamation",
   "types": [
    "Sorcery"
   ],
   "cmc": 3,
   "image": "",
   "colors": [
    "W"
   ],
   "color_identity": [
    "W"
   ],
   "mana_cost": "{2}{W}",
   "url": "https://scryfall.com/card/mh3/267/sevinnes-reclamation?utm_source=api",
   "oracle_text": "Return target permanent card with mana value 3 or less from your graveyard to the battlefield. If this spell was cast from a graveyard, you may copy this spell and may choose a new target for the copy.\nFlashback {4}{W} (You may cast this card from your graveyard for its flashback cost. Then exile it.)",
   "appearances": 1
  },
  {
   "name": "Mavren Fein, Dusk Apostle",
   "types": [
    "Legendary",
    "Creature"
   ],
   "sub_types": [
    "Vampire",
    "Cleric"
   ],
   "cmc": 3,
   "image": "",
   "colors": [
    "W"
   ],
   "color_identity": [
    "W"
   ],
   "mana_cost": "{2}{W}",
   "url": "https://scryfall.com/card/lcc/133/mavren-fein-dusk-apostle?utm_source=api",
   "oracle_text": "Whenever one or more nontoken Vampires you control attack, create a 1/1 white Vampire creature token with lifelink.",
   "power": "2",
   "toughness": "2",
   "appearances": 1
  },
  {
   "name": "Werefox Bodyguard",
   "types": [
    "Creature"
   ],
   "sub_types": [
    "Elf",
    "Fox",
    "Knight"
   ],
   "cmc": 3,
   "image": "",
   "colors": [
    "W"
   ],
   "color_identity": [
    "W"
   ],
   "mana_cost": "{1}{W}{W}",
   "url": "https://scryfall.com/card/woe/39/werefox-bodyguard?utm_source=api",
   "oracle_text": "Flash\nWhen this creature enters, exile up to one other target non-Fox creature until this creature leaves the battlefield.\n{1}{W}, Sacrifice this creature: You gain 2 life.",
   "power": "2",
   "toughness": "2",
   "appearances": 1
  },
  {
   "name": "Mulldrifter",
   "types": [
    "Creature"
   ],
   "sub_types": [
    "Elemental"
   ],
   "cmc": 5,
   "image": "",
   "colors": [
    "U"
   ],
   "color_identity": [
    "U"
   ],
   "mana_cost": "{4}{U}",
   "url": "https://scryfall.com/card/mkc/111/mulldrifter?utm_source=api",
   "oracle_text": "Flying\nWhen this creature enters, draw two cards.\nEvoke {2}{U} (You may cast this spell for its evoke cost. If you do, it's sacrificed when it enters.)",
   "power": "2",
   "toughness": "2",
   "appearances": 1
  },
  {
   "name": "Perilous Myr",
   "types": [
    "Artifact",
    "Creature"
   ],
   "sub_types": [
    "Phyrexian",
    "Myr"
   ],
   "cmc": 2,
   "image": "",
   "colors": [],
   "color_identity": [],
   "mana_cost": "{2}",
   "url": "https://scryfall.com/card/cmr/330/perilous-myr?utm_source=api",
   "oracle_text": "When this creature dies, it deals 2 damage to any target.",
   "power": "1",
   "toughness": "1",
   "appearances": 1
  },
  {
   "name": "Arid Mesa",
   "types": [
    "Land"
   ],
   "cmc": 0,
   "image": "",
   "colors": [],
   "color_identity": [],
   "mana_cost": "",
   "url": "https://scryfall.com/card/mh2/244/arid-mesa?utm_source=api",
   "oracle_text": "{T}, Pay 1 life, Sacrifice this land: Search your library for a Mountain or Plains card, put it onto the battlefield, then shuffle.",
   "appearances": 1
  },
  {
   "name": "Murderous Redcap",
   "types": [
    "Creature"
   ],
   "sub_types": [
    "Goblin",
    "Assassin"
   ],
   "cmc": 4,
   "image": "",
   "colors": [
    "B",
    "R"
   ],
   "color_identity": [
    "B",
    "R"
   ],
   "mana_cost": "{2}{B/R}{B/R}",
   "url": "https://scryfall.com/card/uma/217/murderous-redcap?utm_source=api",
   "oracle_text": "When this creature enters, it deals damage equal to its power to any target.\nPersist (When this creature dies, if it had no -1/-1 counters on it, return it to the battlefield under its owner's control with a -1/-1 counter on it.)",
   "power": "2",
   "toughness": "2",
   "appearances": 1
  },
  {
   "name": "Eiganjo, Seat of the Empire",
   "types": [
    "Legendary",
    "Land"
   ],
   "cmc": 0,
   "image": "",
   "colors": [],
   "color_identity": [
    "W"
   ],
   "mana_cost": "",
   "url": "https://scryfall.com/card/neo/268/eiganjo-seat-of-the-empire?utm_source=api",
   "oracle_text": "{T}: Add {W}.\nChannel — {2}{W}, Discard this card: It deals 4 damage to target attacking or blocking creature. This ability costs {1} less to activate for each legendary creature you control.",
   "appearances": 1
  },
  {
   "name": "Raise the Alarm",
   "types": [
    "Instant"
   ],
   "cmc": 2,
   "image": "",
   "colors": [
    "W"
   ],
   "color_identity": [
    "W"
   ],
   "mana_cost": "{1}{W}",
   "url": "https://scryfall.com/card/cmr/41/raise-the-alarm?utm_source=api",
   "oracle_text": "Create two 1/1 white Soldier creature tokens.",
   "appearances": 1
  },
  {
   "name": "Flames of the Firebrand",
   "types": [
    "Sorcery"
   ],
   "cmc": 3,
   "image": "",
   "colors": [
    "R"
   ],
   "color_identity": [
    "R"
   ],
   "mana_cost": "{2}{R}",
   "url": "https://scryfall.com/card/jmp/317/flames-of-the-firebrand?utm_source=api",
   "oracle_text": "Flames of the Firebrand deals 3 damage divided as you choose among one, two, or three targets.",
   "appearances": 1
  },
  {
   "name": "Field of the Dead",
   "types": [
    "Land"
   ],
   "cmc": 0,
   "image": "",
   "colors": [],
   "color_identity": [],
   "mana_cost": "",
   "url": "https://scryfall.com/card/m20/247/field-of-the-dead?utm_source=api",
   "oracle_text": "This land enters tapped.\n{T}: Add {C}.\nWhenever this land or another land you control enters, if you control seven or more lands with different names, create a 2/2 black Zombie creature token.",
   "appearances": 1
  },
  {
   "name": "Hallowed Fountain",
   "types": [
    "Land"
   ],
   "sub_types": [
    "Plains",
    "Island"
   ],
   "cmc": 0,
   "image": "",
   "colors": [],
   "color_identity": [
    "U",
    "W"
   ],
   "mana_cost": "",
   "url": "https://scryfall.com/card/rvr/280/hallowed-fountain?utm_source=api",
   "oracle_text": "({T}: Add {W} or {U}.)\nAs this land enters, you may pay 2 life. If you don't, it enters tapped.",
   "appearances": 1
  },
  {
   "name": "Saheeli, Sublime Artificer",
   "types": [
    "Legendary",
    "Planeswalker"
   ],
   "sub_types": [
    "Saheeli"
   ],
   "cmc": 3,
   "image": "",
   "colors": [
    "R",
    "U"
   ],
   "color_identity": [
    "R",
    "U"
   ],
   "mana_cost": "{1}{U/R}{U/R}",
   "url": "https://scryfall.com/card/cmm/935/saheeli-sublime-artificer?utm_source=api",
   "oracle_text": "Whenever you cast a noncreature spell, create a 1/1 colorless Servo artifact creature token.\n−2: Target artifact you control becomes a copy of another target artifact or creature you control until end of turn, except it's an artifact in addition to its other types.",
   "appearances": 1
  },
  {
   "name": "Plains",
   "types": [
    "Basic",
    "Land"
   ],
   "sub_types": [
    "Plains"
   ],
   "cmc": 0,
   "image": "",
   "colors": [],
   "color_identity": [
    "W"
   ],
   "mana_cost": "",
   "url": "https://scryfall.com/card/tla/282/plains?utm_source=api",
   "oracle_text": "({T}: Add {W}.)",
   "appearances": 1
  },
  {
   "name": "Swamp",
   "types": [
    "Basic",
    "Land"
   ],
   "sub_types": [
    "Swamp"
   ],
   "cmc": 0,
   "image": "",
   "colors": [],
   "color_identity": [
    "B"
   ],
   "mana_cost": "",
   "url": "https://scryfall.com/card/tla/284/swamp?utm_source=api",
   "oracle_text": "({T}: Add {B}.)",
   "appearances": 1
  },
  {
   "name": "Mountain",
   "types": [
    "Basic",
    "Land"
   ],
   "sub_types": [
    "Mountain"
   ],
   "cmc": 0,
   "image": "",
   "colors": [],
   "color_identity": [
    "R"
   ],
   "mana_cost": "",
   "url": "https://scryfall.com/card/tla/285/mountain?utm_source=api",
   "oracle_text": "({T}: Add {R}.)",
   "appearances": 1
  }
 ],
 "sideboard": [
  {
   "name": "Consider",
   "types": [
    "Instant"
   ],
   "cmc": 1,
   "image": "",
   "colors": [
    "U"
   ],
   "color_identity": [
    "U"
   ],
   "mana_cost": "{U}",
   "url": "https://scryfall.com/card/tdc/148/consider?utm_source=api",
   "oracle_text": "Surveil 1. (Look at the top card of your library. You may put it into your graveyard.)\nDraw a card."
  },
  {
   "name": "Arcbound Tracker",
   "types": [
    "Artifact",
    "Creature"
   ],
   "sub_types": [
    "Dog"
   ],
   "cmc": 3,
   "image": "",
   "colors": [
    "R"
   ],
   "color_identity": [
    "R"
   ],
   "mana_cost": "{2}{R}",
   "url": "https://scryfall.com/card/mh2/112/arcbound-tracker?utm_source=api",
   "oracle_text": "Menace\nModular 2 (This creature enters with two +1/+1 counters on it. When it dies, you may put its +1/+1 counters on target artifact creature.)\nWhenever you cast a spell other than your first spell each turn, put a +1/+1 counter on this creature.",
   "power": "0",
   "toughness": "0"
  },
  {
   "name": "Hedge Maze",
   "types": [
    "Land"
   ],
   "sub_types": [
    "Forest",
    "Island"
   ],
   "cmc": 0,
   "image": "",
   "colors": [],
   "color_identity": [
    "G",
    "U"
   ],
   "mana_cost": "",
   "url": "https://scryfall.com/card/mkm/262/hedge-maze?utm_source=api",
   "oracle_text": "({T}: Add {G} or {U}.)\nThis land enters tapped.\nWhen this land enters, surveil 1. (Look at the top card of your library. You may put it into your graveyard.)"
  },
  {
   "name": "Stern Scolding",
   "types": [
    "Instant"
   ],
   "cmc": 1,
   "image": "",
   "colors": [
    "U"
   ],
   "color_identity": [
    "U"
   ],
   "mana_cost": "{U}",
   "url": "https://scryfall.com/card/ltr/71/stern-scolding?utm_source=api",
   "oracle_text": "Counter target creature spell with power or toughness 2 or less."
  },
  {
   "name": "Hostage Taker",
   "types": [
    "Creature"
   ],
   "sub_types": [
    "Human",
    "Pirate"
   ],
   "cmc": 4,
   "image": "",
   "colors": [
    "B",
    "U"
   ],
   "color_identity": [
    "B",
    "U"
   ],
   "mana_cost": "{2}{U}{B}",
   "url": "https://scryfall.com/card/otc/231/hostage-taker?utm_source=api",
   "oracle_text": "When this creature enters, exile another target creature or artifact until this creature leaves the battlefield. You may cast that card for as long as it remains exiled, and mana of any type can be spent to cast that spell.",
   "power": "2",
   "toughness": "3"
  },
  {
   "name": "Dina, Soul Steeper",
   "types": [
    "Legendary",
    "Creature"
   ],
   "sub_types": [
    "Dryad",
    "Druid"
   ],
   "cmc": 2,
   "image": "",
   "colors": [
    "B",
    "G"
   ],
   "color_identity": [
    "B",
    "G"
   ],
   "mana_cost": "{B}{G}",
   "url": "https://scryfall.com/card/stx/178/dina-soul-steeper?utm_source=api",
   "oracle_text": "Whenever you gain life, each opponent loses 1 life.\n{1}, Sacrifice another creature: Dina gets +X/+0 until end of turn, where X is the sacrificed creature's power.",
   "power": "1",
   "toughness": "3",
   "appearances": 1
  },
  {
   "name": "Lodestone Myr",
   "types": [
    "Artifact",
    "Creature"
   ],
   "sub_types": [
    "Myr"
   ],
   "cmc": 4,
   "image": "",
   "colors": [],
   "color_identity": [],
   "mana_cost": "{4}",
   "url": "https://scryfall.com/card/mm2/220/lodestone-myr?utm_source=api",
   "oracle_text": "Trample\nTap an untapped artifact you control: This creature gets +1/+1 until end of turn.",
   "power": "2",
   "toughness": "2"
  },
  {
   "name": "Candy Trail",
   "types": [
    "Artifact"
   ],
   "sub_types": [
    "Food",
    "Clue"
   ],
   "cmc": 1,
   "image": "",
   "colors": [],
   "color_identity": [],
   "mana_cost": "{1}",
   "url": "https://scryfall.com/card/woe/243/candy-trail?utm_source=api",
   "oracle_text": "When this artifact enters, scry 2.\n{2}, {T}, Sacrifice this artifact: You gain 3 life and draw a card.",
   "appearances": 1
  }
 ]
}