{
 "labels": ["sacrifice", "control"],
 "player": "xander",
 "date": "2023-04-27",
 "wins": 1,
 "losses": 0,
 "ties": 0,
 "mainboard": [
  {
   "name": "Foreboding Ruins",
   "types": [
    "Land"
   ],
   "cmc": 0,
   "image": "",
   "colors": [],
   "url": "https://scryfall.com/card/dmc/211/foreboding-ruins?utm_source=api"
  },
  {
   "name": "Dragonskull Summit",
   "types": [
    "Land"
   ],
   "cmc": 0,
   "image": "",
   "colors": [],
   "url": "https://scryfall.com/card/dmc/207/dragonskull-summit?utm_source=api"
  },
  {
   "name": "Hellion Eruption",
   "types": [
    "Sorcery"
   ],
   "cmc": 6,
   "image": "",
   "colors": [
    "R"
   ],
   "url": "https://scryfall.com/card/pca/45/hellion-eruption?utm_source=api"
  },
  {
   "name": "Vampire Aristocrat",
   "types": [
    "Creature"
   ],
   "sub_types": [
    "Vampire",
    "Rogue",
    "Noble"
   ],
   "cmc": 3,
   "image": "",
   "colors": [
    "B"
   ],
   "url": "https://scryfall.com/card/mm3/86/vampire-aristocrat?utm_source=api"
  },
  {
   "name": "Paladin of the Bloodstained",
   "types": [
    "Creature"
   ],
   "sub_types": [
    "Vampire",
    "Knight"
   ],
   "cmc": 4,
   "image": "",
   "colors": [
    "W"
   ],
   "url": "https://scryfall.com/card/xln/25/paladin-of-the-bloodstained?utm_source=api"
  },
  {
   "name": "Kathari Bomber",
   "types": [
    "Creature"
   ],
   "sub_types": [
    "Bird",
    "Shaman"
   ],
   "cmc": 3,
   "image": "",
   "colors": [
    "B",
    "R"
   ],
   "url": "https://scryfall.com/card/mm3/172/kathari-bomber?utm_source=api"
  },
  {
   "name": "Clifftop Retreat",
   "types": [
    "Land"
   ],
   "cmc": 0,
   "image": "",
   "colors": [],
   "url": "https://scryfall.com/card/dom/239/clifftop-retreat?utm_source=api"
  },
  {
   "name": "Lightning Bolt",
   "types": [
    "Instant"
   ],
   "cmc": 1,
   "image": "",
   "colors": [
    "R"
   ],
   "url": "https://scryfall.com/card/2x2/117/lightning-bolt?utm_source=api"
  },
  {
   "name": "Isolated Chapel",
   "types": [
    "Land"
   ],
   "cmc": 0,
   "image": "",
   "colors": [],
   "url": "https://scryfall.com/card/dom/241/isolated-chapel?utm_source=api"
  },
  {
   "name": "Mavren Fein, Dusk Apostle",
   "types": [
    "Legendary",
    "Creature"
   ],
   "sub_types": [
    "Vampire",
    "Cleric"
   ],
   "cmc": 3,
   "image": "",
   "colors": [
    "W"
   ],
   "url": "https://scryfall.com/card/xln/24/mavren-fein-dusk-apostle?utm_source=api"
  },
  {
   "name": "Terramorphic Expanse",
   "types": [
    "Land"
   ],
   "cmc": 0,
   "image": "",
   "colors": [],
   "url": "https://scryfall.com/card/pctb/85/terramorphic-expanse?utm_source=api"
  },
  {
   "name": "Orzhov Racketeers",
   "types": [
    "Creature"
   ],
   "sub_types": [
    "Human",
    "Rogue"
   ],
   "cmc": 5,
   "image": "",
   "colors": [
    "B"
   ],
   "url": "https://scryfall.com/card/rna/80/orzhov-racketeers?utm_source=api"
  },
  {
   "name": "Gravedigger",
   "types": [
    "Creature"
   ],
   "sub_types": [
    "Zombie"
   ],
   "cmc": 4,
   "image": "",
   "colors": [
    "B"
   ],
   "url": "https://scryfall.com/card/m20/103/gravedigger?utm_source=api"
  },
  {
   "name": "Blinding Mage",
   "types": [
    "Creature"
   ],
   "sub_types": [
    "Human",
    "Wizard"
   ],
   "cmc": 2,
   "image": "",
   "colors": [
    "W"
   ],
   "url": "https://scryfall.com/card/ima/13/blinding-mage?utm_source=api"
  },
  {
   "name": "Vampire Hexmage",
   "types": [
    "Creature"
   ],
   "sub_types": [
    "Vampire",
    "Shaman"
   ],
   "cmc": 2,
   "image": "",
   "colors": [
    "B"
   ],
   "url": "https://scryfall.com/card/2xm/112/vampire-hexmage?utm_source=api"
  },
  {
   "name": "Scoured Barrens",
   "types": [
    "Land"
   ],
   "cmc": 0,
   "image": "",
   "colors": [],
   "url": "https://scryfall.com/card/mom/272/scoured-barrens?utm_source=api"
  },
  {
   "name": "Makeshift Munitions",
   "types": [
    "Enchantment"
   ],
   "cmc": 2,
   "image": "",
   "colors": [
    "R"
   ],
   "url": "https://scryfall.com/card/cmr/191/makeshift-munitions?utm_source=api"
  },
  {
   "name": "Rockslide Elemental",
   "types": [
    "Creature"
   ],
   "sub_types": [
    "Elemental"
   ],
   "cmc": 3,
   "image": "",
   "colors": [
    "R"
   ],
   "url": "https://scryfall.com/card/hop/63/rockslide-elemental?utm_source=api"
  },
  {
   "name": "Disfigure",
   "types": [
    "Instant"
   ],
   "cmc": 1,
   "image": "",
   "colors": [
    "B"
   ],
   "url": "https://scryfall.com/card/bro/91/disfigure?utm_source=api"
  },
  {
   "name": "Liliana's Mastery",
   "types": [
    "Enchantment"
   ],
   "cmc": 5,
   "image": "",
   "colors": [
    "B"
   ],
   "url": "https://scryfall.com/card/mic/123/lilianas-mastery?utm_source=api"
  },
  {
   "name": "Plains",
   "types": [
    "Basic",
    "Land"
   ],
   "sub_types": [
    "Plains"
   ],
   "cmc": 0,
   "image": "",
   "colors": [],
   "url": "https://scryfall.com/card/who/197/plains?utm_source=api"
  },
  {
   "name": "Plains",
   "types": [
    "Basic",
    "Land"
   ],
   "sub_types": [
    "Plains"
   ],
   "cmc": 0,
   "image": "",
   "colors": [],
   "url": "https://scryfall.com/card/who/197/plains?utm_source=api"
  },
  {
   "name": "Plains",
   "types": [
    "Basic",
    "Land"
   ],
   "sub_types": [
    "Plains"
   ],
   "cmc": 0,
   "image": "",
   "colors": [],
   "url": "https://scryfall.com/card/who/197/plains?utm_source=api"
  },
  {
   "name": "Iona's Judgment",
   "types": [
    "Sorcery"
   ],
   "cmc": 5,
   "image": "",
   "colors": [
    "W"
   ],
   "url": "https://scryfall.com/card/cmr/25/ionas-judgment?utm_source=api"
  },
  {
   "name": "Soul Warden",
   "types": [
    "Creature"
   ],
   "sub_types": [
    "Human",
    "Cleric"
   ],
   "cmc": 1,
   "image": "",
   "colors": [
    "W"
   ],
   "url": "https://scryfall.com/card/mm3/24/soul-warden?utm_source=api"
  },
  {
   "name": "Pacifism",
   "types": [
    "Enchantment"
   ],
   "sub_types": [
    "Aura"
   ],
   "cmc": 2,
   "image": "",
   "colors": [
    "W"
   ],
   "url": "https://scryfall.com/card/jmp/125/pacifism?utm_source=api"
  },
  {
   "name": "Furycalm Snarl",
   "types": [
    "Land"
   ],
   "cmc": 0,
   "image": "",
   "colors": [],
   "url": "https://scryfall.com/card/moc/404/furycalm-snarl?utm_source=api"
  },
  {
   "name": "Ajani's Pridemate",
   "types": [
    "Creature"
   ],
   "sub_types": [
    "Cat",
    "Soldier"
   ],
   "cmc": 2,
   "image": "",
   "colors": [
    "W"
   ],
   "url": "https://scryfall.com/card/war/4/ajanis-pridemate?utm_source=api"
  },
  {
   "name": "Mountain",
   "types": [
    "Basic",
    "Land"
   ],
   "sub_types": [
    "Mountain"
   ],
   "cmc": 0,
   "image": "",
   "colors": [],
   "url": "https://scryfall.com/card/who/203/mountain?utm_source=api"
  },
  {
   "name": "Mountain",
   "types": [
    "Basic",
    "Land"
   ],
   "sub_types": [
    "Mountain"
   ],
   "cmc": 0,
   "image": "",
   "colors": [],
   "url": "https://scryfall.com/card/who/203/mountain?utm_source=api"
  },
  {
   "name": "Cinder Barrens",
   "types": [
    "Land"
   ],
   "cmc": 0,
   "image": "",
   "colors": [],
   "url": "https://scryfall.com/card/c19/235/cinder-barrens?utm_source=api"
  },
  {
   "name": "Gwyllion Hedge-Mage",
   "types": [
    "Creature"
   ],
   "sub_types": [
    "Hag",
    "Wizard"
   ],
   "cmc": 3,
   "image": "",
   "colors": [
    "B",
    "W"
   ],
   "url": "https://scryfall.com/card/cma/201/gwyllion-hedge-mage?utm_source=api"
  },
  {
   "name": "Scavenger Drake",
   "types": [
    "Creature"
   ],
   "sub_types": [
    "Drake"
   ],
   "cmc": 4,
   "image": "",
   "colors": [
    "B"
   ],
   "url": "https://scryfall.com/card/mm2/93/scavenger-drake?utm_source=api"
  },
  {
   "name": "Swamp",
   "types": [
    "Basic",
    "Land"
   ],
   "sub_types": [
    "Swamp"
   ],
   "cmc": 0,
   "image": "",
   "colors": [],
   "url": "https://scryfall.com/card/who/201/swamp?utm_source=api"
  },
  {
   "name": "Swamp",
   "types": [
    "Basic",
    "Land"
   ],
   "sub_types": [
    "Swamp"
   ],
   "cmc": 0,
   "image": "",
   "colors": [],
   "url": "https://scryfall.com/card/who/201/swamp?utm_source=api"
  },
  {
   "name": "Swamp",
   "types": [
    "Basic",
    "Land"
   ],
   "sub_types": [
    "Swamp"
   ],
   "cmc": 0,
   "image": "",
   "colors": [],
   "url": "https://scryfall.com/card/who/201/swamp?utm_source=api"
  },
  {
   "name": "Goblin Arsonist",
   "types": [
    "Creature"
   ],
   "sub_types": [
    "Goblin",
    "Shaman"
   ],
   "cmc": 1,
   "image": "",
   "colors": [
    "R"
   ],
   "url": "https://scryfall.com/card/m21/147/goblin-arsonist?utm_source=api"
  },
  {
   "name": "Pitiless Pontiff",
   "types": [
    "Creature"
   ],
   "sub_types": [
    "Vampire",
    "Cleric"
   ],
   "cmc": 2,
   "image": "",
   "colors": [
    "B",
    "W"
   ],
   "url": "https://scryfall.com/card/rna/194/pitiless-pontiff?utm_source=api"
  },
  {
   "name": "Hordeling Outburst",
   "types": [
    "Sorcery"
   ],
   "cmc": 3,
   "image": "",
   "colors": [
    "R"
   ],
   "url": "https://scryfall.com/card/a25/134/hordeling-outburst?utm_source=api"
  },
  {
   "name": "Jinxed Idol",
   "types": [
    "Artifact"
   ],
   "cmc": 2,
   "image": "",
   "colors": [],
   "url": "https://scryfall.com/card/tpr/224/jinxed-idol?utm_source=api"
  }
 ],
 "sideboard": []
}
